{
    "data": [
        {   
            "path": "ajansmobil2",
            "id": "ajansmobil",
            "tiktok": "17923",
            "instagram": "17142",
            "title": "Profesyonel Fotoğraf Çekimi İle Markanızı parlatın!",
            "keywords": "Profesyonel Fotoğraf Çekimi, Marka Hikayesi, Görsel İçerik, Ürün Çekimi, Portre Fotoğrafçılığı, Profesyonel İmaj, Marka Kimliği, Görsel Güç, Fotoğraf Hizmetleri, Yaratıcı Çekim, Profesyonel Kalite, Görsel Pazarlama, Marka Farkındalığı, Fotoğraf Ajansı, Görsel İletişim, Profesyonel Hizmet, Marka Görünürlüğü, Etkili Görseller",
            "description": "MARKANIZIN HİKAYESİNİ FOTOĞRAFLARLA ANLATIN!\n\nProfesyonel fotoğraf çekimi ile markanızın değerini görsel olarak yansıtın ve müşterilerinizi etkileyin!\n\nNEDEN PROFESYONEL FOTOĞRAF ÇEKİMİ?\n• Marka hikayenizi görsel olarak anlatır\n• Ürün ve hizmet kalitenizi yansıtır\n• Potansiyel müşterilerinizi büyüler\n• Rakiplerinizden ayrışmanızı sağlar\n• Profesyonel imaj oluşturur\n\nAJANS MOBİL FOTOĞRAF ÇÖZÜMLERİ:\n• Ürün çekimi ve portre fotoğrafçılığı\n• Profesyonel ekipman ve teknik\n• Yaratıcı kompozisyon ve ışıklandırma\n• Post-prodüksiyon ve retuş\n• Marka kimliğinize uygun çekim\n\nGöz alıcı görsellerle potansiyel müşterilerinizi büyüleyin!\n\nHemen iletişime geçin ve görsel gücünüzü keşfedin!\n\n#ProfesyonelFotoğraf #AjansMobil #FotoğrafÇekimi #MarkaHikayesi #Görselİçerik #ÜrünÇekimi #PortreFotoğrafçılığı #Profesyonelİmaj #MarkaKimliği #GörselGüç #FotoğrafHizmetleri #YaratıcıÇekim #ProfesyonelKalite #GörselPazarlama #MarkaFarkındalığı #FotoğrafAjansı #Görselİletişim #ProfesyonelHizmet #MarkaGörünürlüğü #EtkiliGörseller"
        }
    ]
}